surfepy.libs/libsurfe_lib-6cdfc892.so
surfepy.libs/libgomp-f7e03b3e.so.1.0.0
surfepy.libs/libmath_lib-80868773.so
surfepy/__init__.py
surfepy/libsurfe_lib.so
surfepy/libmath_lib.so
surfepy/_surfepy.cpython-39-x86_64-linux-gnu.so
surfepy-0.52.dist-info/top_level.txt
surfepy-0.52.dist-info/WHEEL
surfepy-0.52.dist-info/RECORD
surfepy-0.52.dist-info/METADATA
