Metadata-Version: 2.1
Name: surfepy
Version: 0.52
Summary: python bindings for surfe - geological interpolator using rbf
Home-page: UNKNOWN
Author: Michael Hillier
Author-email: UNKNOWN
License: MIT
Platform: UNKNOWN
